<?xml version="1.0" encoding="UTF-8"?>
<con:soapui-project id="a7340c54-e615-4865-ba93-f7b0ffa37a76" created="3.40.2" activeEnvironment="Default" name="REST Project 4" resourceRoot="" updated="3.40.2 2022-07-27T09:18:31Z" encryptionMode="Not encrypted" abortOnError="false" runType="SEQUENTIAL" soapui-version="5.7.0" xmlns:con="http://eviware.com/soapui/config">
  <con:settings/>
  <con:interface xsi:type="con:RestService" id="bd039f64-f217-4b51-a534-10115189137c" wadlVersion="http://wadl.dev.java.net/2009/02" name="http://ipwhois.app" type="rest" xmlns:xsi="http://www.w3.org/2001/XMLSchema-instance">
    <con:settings/>
    <con:definitionCache type="TEXT" rootPart=""/>
    <con:endpoints>
      <con:endpoint>http://ipwhois.app</con:endpoint>
    </con:endpoints>
    <con:resource name="IP" path="/json/{IP}" id="348688aa-6a33-4fbb-aeae-92235b99a2c3">
      <con:settings/>
      <con:parameters/>
      <con:method name="IP" id="dc81779c-5444-43e8-a43f-cdbc5dc67c82" method="GET">
        <con:settings/>
        <con:parameters>
          <con:parameter required="true">
            <con:name>IP</con:name>
            <con:value>IP</con:value>
            <con:style>TEMPLATE</con:style>
            <con:default>IP</con:default>
            <con:path xsi:nil="true"/>
            <con:description xsi:nil="true"/>
          </con:parameter>
        </con:parameters>
        <con:representation type="RESPONSE">
          <con:mediaType>application/json; charset=utf-8</con:mediaType>
          <con:status>200</con:status>
          <con:params/>
          <con:element xmlns:ns="http://ipwhois.app/json/66.12.25.226">ns:Response</con:element>
        </con:representation>
        <con:request name="Request 1" id="3b47038d-1f7e-4aad-957b-13a0d799572f" mediaType="application/json">
          <con:settings/>
          <con:endpoint>http://ipwhois.app</con:endpoint>
          <con:credentials>
            <con:selectedAuthProfile>No Authorization</con:selectedAuthProfile>
            <con:authType>No Authorization</con:authType>
          </con:credentials>
          <con:parameters>
            <con:entry key="IP" value="IP"/>
          </con:parameters>
          <con:parameterOrder>
            <con:entry>IP</con:entry>
          </con:parameterOrder>
        </con:request>
      </con:method>
    </con:resource>
  </con:interface>
  <con:testSuite id="3fd9c271-eac5-49d1-be8e-a9f63c8db816" name="http://ipwhois.app Test Suite">
    <con:settings/>
    <con:runType>SEQUENTIAL</con:runType>
    <con:testCase id="c1587735-0294-4b9a-81a4-464c516dd966" discardOkResults="false" failOnError="true" failTestCaseOnErrors="true" keepSession="false" name="http://ipwhois.app Test Case 1" searchProperties="true" timeout="0" maxResults="0">
      <con:settings/>
      <con:testStep type="datasource" name="DataSource 2" id="fd601bcb-8ed9-4c75-9d56-1ee4e698ac40">
        <con:settings/>
        <con:config xsi:type="con:DataSourceStep" xmlns:xsi="http://www.w3.org/2001/XMLSchema-instance">
          <con:dataSource type="Excel">
            <con:configuration>
              <file>C:/Users/03221V744/Documents/IP_Address.xlsx</file>
              <worksheet/>
              <cell>A2</cell>
              <ignoreEmpty>false</ignoreEmpty>
              <evaluateFormulas>false</evaluateFormulas>
            </con:configuration>
          </con:dataSource>
          <con:shared>false</con:shared>
          <con:restartShared>false</con:restartShared>
          <con:property>IPAddress</con:property>
          <con:restartOnRun>true</con:restartOnRun>
        </con:config>
      </con:testStep>
      <con:testStep type="datasource" name="DataSource" id="87048623-7963-4c0d-b813-8b4dee833ce1">
        <con:settings/>
        <con:config xsi:type="con:DataSourceStep" xmlns:xsi="http://www.w3.org/2001/XMLSchema-instance">
          <con:dataSource type="Excel">
            <con:configuration>
              <file>C:/Users/03221V744/Documents/IP_Address.xlsx</file>
              <worksheet/>
              <cell>A2</cell>
              <ignoreEmpty>false</ignoreEmpty>
              <evaluateFormulas>false</evaluateFormulas>
            </con:configuration>
          </con:dataSource>
          <con:shared>false</con:shared>
          <con:restartShared>false</con:restartShared>
          <con:property>136.162.168.21</con:property>
          <con:restartOnRun>true</con:restartOnRun>
        </con:config>
      </con:testStep>
      <con:testStep type="restrequest" name="Request 1" id="8184abd7-ecad-41f3-9f58-ef39e5a29645">
        <con:settings/>
        <con:config service="http://ipwhois.app" resourcePath="/json/{IP}" methodName="IP" xsi:type="con:RestRequestStep" xmlns:xsi="http://www.w3.org/2001/XMLSchema-instance">
          <con:restRequest name="Request 1" id="3b47038d-1f7e-4aad-957b-13a0d799572f" mediaType="application/json">
            <con:settings>
              <con:setting id="com.eviware.soapui.impl.wsdl.WsdlRequest@request-headers">&lt;xml-fragment/></con:setting>
            </con:settings>
            <con:endpoint>http://ipwhois.app</con:endpoint>
            <con:request/>
            <con:originalUri>http://ipwhois.app/json/66.12.25.226</con:originalUri>
            <con:assertion type="Valid HTTP Status Codes" id="d3ebcb96-b35b-4643-817d-a201ffd0fc5b" name="Valid HTTP Status Codes">
              <con:settings/>
              <con:configuration>
                <codes>200</codes>
              </con:configuration>
            </con:assertion>
            <con:assertion type="Response SLA Assertion" id="52b91d12-c30e-4bd9-8370-161d0ee9adc1" name="Response SLA">
              <con:configuration>
                <SLA>200</SLA>
              </con:configuration>
            </con:assertion>
            <con:assertion type="JsonPath Match" id="702926ae-34f6-4591-9a18-3bde08f28cb7" name="JSONPath Match">
              <con:configuration>
                <path>$['country']</path>
                <content>"United States"</content>
                <allowWildcards>false</allowWildcards>
                <ignoreNamspaceDifferences>false</ignoreNamspaceDifferences>
                <ignoreComments>false</ignoreComments>
              </con:configuration>
            </con:assertion>
            <con:credentials>
              <con:selectedAuthProfile>No Authorization</con:selectedAuthProfile>
              <con:authType>No Authorization</con:authType>
            </con:credentials>
            <con:jmsConfig JMSDeliveryMode="PERSISTENT"/>
            <con:parameters>
              <con:entry key="IP" value="${DataSource#136.162.168.21  }"/>
            </con:parameters>
            <con:parameterOrder>
              <con:entry>IP</con:entry>
            </con:parameterOrder>
          </con:restRequest>
        </con:config>
      </con:testStep>
      <con:testStep type="datasourceloop" name="Data Source Loop" id="c4101eb5-d5dd-4a68-ba2f-815474e06e95">
        <con:settings/>
        <con:config>
          <dataSourceStep>DataSource</dataSourceStep>
          <targetStep>Request 1</targetStep>
          <discardResults>true</discardResults>
        </con:config>
      </con:testStep>
      <con:testStep type="datasourceloop" name="Data Source Loop 2" id="9244d1ea-5843-44c7-861a-147c71b61568">
        <con:settings/>
        <con:config>
          <dataSourceStep>DataSource 2</dataSourceStep>
          <targetStep>Request 1</targetStep>
          <discardResults>true</discardResults>
        </con:config>
      </con:testStep>
      <con:testStep type="jdbc" name="JDBC Request" id="8f637d6c-6e79-4d9b-9a85-5f8dfcee6675">
        <con:settings>
          <con:setting id="prettyPrintResponse">true</con:setting>
        </con:settings>
        <con:config xsi:type="con:JdbcRequestTestStep" convertColumnNamesToUpperCase="true" xmlns:xsi="http://www.w3.org/2001/XMLSchema-instance">
          <con:dbConnectionName>MySQL</con:dbConnectionName>
          <con:driver>com.mysql.jdbc.Driver</con:driver>
          <con:connectionString>jdbc:mysql://remotemysql.com:3306/CGpfjlbstY?user=CGpfjlbstY&amp;password=PASS_VALUE</con:connectionString>
          <con:password>Sav3dVDTJ4</con:password>
          <con:connectionProperties/>
          <con:query>Select CGpfjlbstY.petData.petStatus</con:query>
          <con:assertion type="JDBC Status" id="9e22a7c7-d9e8-4090-a033-fd6e996dbae3" name="JDBC Status"/>
          <con:properties/>
        </con:config>
      </con:testStep>
      <con:properties/>
      <con:reportParameters/>
    </con:testCase>
    <con:properties/>
    <con:reportParameters/>
  </con:testSuite>
  <con:requirements/>
  <con:properties/>
  <con:wssContainer/>
  <con:databaseConnectionContainer>
    <con:databaseConnection>
      <con:name>MySQL</con:name>
      <con:driver>com.mysql.jdbc.Driver</con:driver>
      <con:connectionString>jdbc:mysql://remotemysql.com:3306/CGpfjlbstY?user=CGpfjlbstY&amp;password=PASS_VALUE</con:connectionString>
      <con:password>Sav3dVDTJ4</con:password>
      <con:connectionProperties/>
    </con:databaseConnection>
  </con:databaseConnectionContainer>
  <con:jmsConnectionContainer/>
  <con:oAuth2ProfileContainer/>
  <con:oAuth1ProfileContainer/>
  <con:reporting>
    <con:xmlTemplates/>
    <con:parameters/>
  </con:reporting>
  <con:eventHandlers type="RequestFilter.filterRequest" name="RequestFilter.filterRequest">
    <con:script>// Sample event script to add custom HTTP header to all outgoing REST, SOAP and HTTP(S) calls
// This code is often used for adding custom authentication to ReadyAPI functional tests

// If hardcoding the token, uncomment and change line 5
// token = '4567'

// If your token is parameterized in Project level custom property, uncomment line 8
// token = request.parent.testCase.testSuite.project.getProperty('auth_token').getValue()

// To modify all outgoing calls, remove comments from lines 11 to 16
// headers = request.requestHeaders
// if (headers.containsKey('auth_token2') == false) {
//   headers.put('auth_token2', token)
//   request.requestHeaders = headers
// }</con:script>
  </con:eventHandlers>
  <con:eventHandlers type="TestRunListener.afterStep" name="TestRunListener.afterStep">
    <con:script>// Save all test step results into files
// Change the directory path in line 5 to a location where you want to store details
// then uncomment lines 5 to 10

// filePath = 'C:\\tempOutputDirectory\\'
// fos = new java.io.FileOutputStream(filePath + testStepResult.testStep.label + '.txt', true)
// pw = new java.io.PrintWriter(fos)
// testStepResult.writeTo(pw)
// pw.close()
// fos.close()</con:script>
  </con:eventHandlers>
  <con:authRepository/>
  <con:tags/>
</con:soapui-project>